README.md
setup.py
xmaios/Base.py
xmaios/Bot.py
xmaios/Certificate.py
xmaios/Constants.py
xmaios/Intercept.py
xmaios/Log.py
xmaios/Nlu.py
xmaios/Request.py
xmaios/Response.py
xmaios/Session.py
xmaios/SysType.py
xmaios/Utils.py
xmaios/__init__.py
xmaios/card/BaseCard.py
xmaios/card/CardType.py
xmaios/card/ImageCard.py
xmaios/card/LinkAccountCard.py
xmaios/card/ListCard.py
xmaios/card/ListCardItem.py
xmaios/card/StandardCard.py
xmaios/card/TextCard.py
xmaios/card/WebCard.py
xmaios/card/__init__.py
xmaios/directive/BaseDirective.py
xmaios/directive/__init__.py
xmaios/directive/AppLauncher/LaunchApp.py
xmaios/directive/AppLauncher/__init__.py
xmaios/directive/AudioPlayer/AudioItemTypeEnum.py
xmaios/directive/AudioPlayer/AudioPlayerInfo.py
xmaios/directive/AudioPlayer/AudioPlayerInfoContent.py
xmaios/directive/AudioPlayer/Play.py
xmaios/directive/AudioPlayer/PlayBehaviorEnum.py
xmaios/directive/AudioPlayer/PlayerInfo.py
xmaios/directive/AudioPlayer/Stop.py
xmaios/directive/AudioPlayer/StreamFormatEnum.py
xmaios/directive/AudioPlayer/__init__.py
xmaios/directive/AudioPlayer/Control/BaseButton.py
xmaios/directive/AudioPlayer/Control/Button.py
xmaios/directive/AudioPlayer/Control/FavoriteButton.py
xmaios/directive/AudioPlayer/Control/LyricButton.py
xmaios/directive/AudioPlayer/Control/NextButton.py
xmaios/directive/AudioPlayer/Control/PlayPauseButton.py
xmaios/directive/AudioPlayer/Control/PreviousButton.py
xmaios/directive/AudioPlayer/Control/RadioButton.py
xmaios/directive/AudioPlayer/Control/RecommendButton.py
xmaios/directive/AudioPlayer/Control/RefreshButton.py
xmaios/directive/AudioPlayer/Control/RepeatButton.py
xmaios/directive/AudioPlayer/Control/RepeatButtonEnum.py
xmaios/directive/AudioPlayer/Control/ShowFavoriteListButton.py
xmaios/directive/AudioPlayer/Control/ShowPlayListButton.py
xmaios/directive/AudioPlayer/Control/ThumbsUpDownButton.py
xmaios/directive/AudioPlayer/Control/ThumbsUpDownButtonEnum.py
xmaios/directive/AudioPlayer/Control/__init__.py
xmaios_bot.egg-info/PKG-INFO
xmaios_bot.egg-info/SOURCES.txt
xmaios_bot.egg-info/dependency_links.txt
xmaios_bot.egg-info/requires.txt
xmaios_bot.egg-info/top_level.txt