Metadata-Version: 1.0
Name: xmaios-bot
Version: 0.0.1
Summary: Third party XmaiOS Bot Python SDK
Home-page: UNKNOWN
Author: UNKNOWN
Author-email: UNKNOWN
License: UNKNOWN
Keywords: xmaios bot
Platform: py3
